autopimms/__init__.py
autopimms/autopimms copy.py
autopimms/dataobj.py
autopimms/fetch.py
autopimms/main.py
autopimms-1.1.0.dist-info/LICENSE
autopimms-1.1.0.dist-info/METADATA
autopimms-1.1.0.dist-info/WHEEL
autopimms-1.1.0.dist-info/top_level.txt
autopimms-1.1.0.dist-info/RECORD
